masterchess
tests
