Metadata-Version: 1.1
Name: chessmaster
Version: 1.1.1
Summary: Chess Master Challenge
Home-page: https://github.com/fabiobatalha/chess_master
Author: Fabio Batalha
Author-email: fabiobatalha@gmail.com
License: UNKNOWN
Platform: UNKNOWN
Classifier: Development Status :: 4 - Beta
Classifier: Intended Audience :: Developers
Classifier: Programming Language :: Python :: 3
Classifier: Programming Language :: Python :: 2.7
